Workbook

Sheet Dashboard
A1: SALES PERFORMANCE DASHBOARD
A3: Total Sales | C3: Total Profit | E3: Total Orders | G3: Avg Discount | I3: Top Region | K3: Top Category
A4: 195217.76 | C4: 68287.01 | E4: 200 | G4: 0.09725 | I4: West | K4: Books
A8: Month | B8: Sales | C8: Profit
A9: 2024-04 | B9: 19029.96 | C9: 6244.01
A10: 2024-05 | B10: 18507.34 | C10: 6121.35
A11: 2024-06 | B11: 20187.51 | C11: 6918
A12: 2024-07 | B12: 11609.04 | C12: 3743.85
A13: 2024-08 | B13: 10091.7 | C13: 3302.84
A14: 2024-09 | B14: 20533.5 | C14: 7457.52
A15: 2024-10 | B15: 14215.24 | C15: 4861.7
A16: 2024-11 | B16: 20135.03 | C16: 6814.88
A17: 2024-12 | B17: 11120.04 | C17: 3549.99
A18: 2025-01 | B18: 14914.65 | C18: 5763.4
A19: 2025-02 | B19: 14006.36 | C19: 5039.23
A20: 2025-03 | B20: 17655.22 | C20: 7071.39
A21: 2025-04 | B21: 3212.17 | C21: 1398.85
A24: Category | B24: Sales
A25: West | B25: 44083.58 | E25: Books | F25: 47002.46
A26: Central | B26: 43468.33 | E26: Clothing | F26: 41927.59
A27: South | B27: 40248.79 | E27: Electronics | F27: 41044
A28: North | B28: 34975.42 | E28: Furniture | F28: 36612.89
A29: East | B29: 32441.64 | E29: Office Supplies | F29: 28630.82
H42: Key Insights
H43: • Highest region by sales: West (44,083.58).
H44: • Highest product category: Books (47,002.46).
H45: • Top customer ID by total purchase: CUST015 (11,611.06).
H46: • Best monthly sales: 2024-09 (20,533.50).
H47: • Lowest monthly sales: 2025-04 (3,212.17).
H48: • Sales-profit regression R²: 0.598.

Sheet Project Instructions
A1: PR. 2 Analyzer - Completed Workbook
A3: 1. Conditional Formatting – Top 10 customers based on total purchase.
A4: 2. WHAT IF Analysis – Compare total profit at different discount rates.
A5: 3. Linear Regression – Profit vs Sales (equivalent to Excel Data Analysis ToolPak output).
A6: 4. Descriptive Statistics – Sales, Quantity, Discount and Profit.
A7: 5. Monthly Sales Growth – Up/down symbols are added using conditional formatting.
A8: 6. Timestamp – NOW() is added to the dataset.
A9: 7. High-Value Customers – INDEX/MATCH lookup plus filtered Top 10 customer table.
A10: 8. Pivot-style analysis – Total sales by Region and Product Category.
A11: 9. Charts – Bar, Line and Pie charts for KPIs.
A12: 10. Dashboard – KPI summary and visual insights.

Sheet Dataset
A1: Customer_ID | B1: Customer_Name | C1: Region | D1: Product_Category | E1: Sales | F1: Quantity | G1: Discount | H1: Order_Date | I1: Profit | J1: Timestamp
A2: CUST019 | B2: James Davis | C2: West | D2: Books | E2: 1036.09 | F2: 4 | G2: 0.2 | H2: 45392 | I2: 331.55 | J2: =NOW() -> 46301.641
A3: CUST012 | B3: Robert Anderson | C3: West | D3: Clothing | E3: 1101.28 | F3: 3 | G3: 0.2 | H3: 45393 | I3: 440.51 | J3: =NOW() -> 46301.641
A4: CUST017 | B4: James Taylor | C4: East | D4: Books | E4: 713.34 | F4: 17 | G4: 0 | H4: 45396 | I4: 285.34 | J4: =NOW() -> 46301.641
A5: CUST005 | B5: Robert Anderson | C5: South | D5: Electronics | E5: 760.93 | F5: 4 | G5: 0.15 | H5: 45396 | I5: 161.7 | J5: =NOW() -> 46301.641
A6: CUST030 | B6: James Wilson | C6: North | D6: Books | E6: 847 | F6: 12 | G6: 0.2 | H6: 45397 | I6: 271.04 | J6: =NOW() -> 46301.641
A7: CUST007 | B7: Michael Anderson | C7: North | D7: Furniture | E7: 965.64 | F7: 8 | G7: 0.1 | H7: 45398 | I7: 304.18 | J7: =NOW() -> 46301.641
A8: CUST001 | B8: Linda Wilson | C8: West | D8: Electronics | E8: 1317.53 | F8: 12 | G8: 0.05 | H8: 45398 | I8: 312.91 | J8: =NOW() -> 46301.641
A9: CUST026 | B9: Mary Davis | C9: East | D9: Furniture | E9: 1074.47 | F9: 6 | G9: 0.2 | H9: 45401 | I9: 300.85 | J9: =NOW() -> 46301.641
A10: CUST009 | B10: Linda Jackson | C10: Central | D10: Books | E10: 501.54 | F10: 11 | G10: 0.05 | H10: 45401 | I10: 190.59 | J10: =NOW() -> 46301.641
A11: CUST010 | B11: David Thomas | C11: Central | D11: Clothing | E11: 737.31 | F11: 2 | G11: 0.05 | H11: 45401 | I11: 350.22 | J11: =NOW() -> 46301.641
A12: CUST014 | B12: Emma Davis | C12: West | D12: Office Supplies | E12: 1572.82 | F12: 6 | G12: 0.05 | H12: 45402 | I12: 672.38 | J12: =NOW() -> 46301.641
A13: CUST014 | B13: David Thomas | C13: Central | D13: Books | E13: 1343.13 | F13: 14 | G13: 0.15 | H13: 45404 | I13: 456.66 | J13: =NOW() -> 46301.641
... A201: CUST016 | B201: David Thomas | C201: South | D201: Clothing | E201: 928.32 | F201: 2 | G201: 0.05 | H201: 45754 | I201: 440.95 | J201: =NOW() -> 46301.641

Sheet Customer Summary
A1: Customer Purchase Summary - Top 10 Highlighted
A2: Top 10 customers are highlighted in the Total Purchase column.
A3: Customer_ID | B3: Customer_Name | C3: Total Purchase | D3: Total Profit | E3: Orders | F3: Rank
A4: CUST001 | B4: =INDEX(Dataset!$B$2:$B$201,MATCH(A4,Dataset!$A$2:$A$201,0)) -> Linda Wilson | C4: =SUMIF(Dataset!$A$2:$A$201,A4,Dataset!$E$2:$E$201) -> 6549.55 | D4: =SUMIF(Dataset!$A$2:$A$201,A4,Dataset!$I$2:$I$201) -> 1868.77 | E4: =COUNTIF(Dataset!$A$2:$A$201,A4) -> 7 | F4: =RANK(C4,$C$4:$C$33,0) -> 15
A5: CUST002 | B5: =INDEX(Dataset!$B$2:$B$201,MATCH(A5,Dataset!$A$2:$A$201,0)) -> Lisa Davis | C5: =SUMIF(Dataset!$A$2:$A$201,A5,Dataset!$E$2:$E$201) -> 6481.43 | D5: =SUMIF(Dataset!$A$2:$A$201,A5,Dataset!$I$2:$I$201) -> 2210.74 | E5: =COUNTIF(Dataset!$A$2:$A$201,A5) -> 6 | F5: =RANK(C5,$C$4:$C$33,0) -> 17
A6: CUST003 | B6: =INDEX(Dataset!$B$2:$B$201,MATCH(A6,Dataset!$A$2:$A$201,0)) -> Emma Davis | C6: =SUMIF(Dataset!$A$2:$A$201,A6,Dataset!$E$2:$E$201) -> 8490.18 | D6: =SUMIF(Dataset!$A$2:$A$201,A6,Dataset!$I$2:$I$201) -> 2652.75 | E6: =COUNTIF(Dataset!$A$2:$A$201,A6) -> 9 | F6: =RANK(C6,$C$4:$C$33,0) -> 7
A7: CUST004 | B7: =INDEX(Dataset!$B$2:$B$201,MATCH(A7,Dataset!$A$2:$A$201,0)) -> Lisa Thomas | C7: =SUMIF(Dataset!$A$2:$A$201,A7,Dataset!$E$2:$E$201) -> 7813.59 | D7: =SUMIF(Dataset!$A$2:$A$201,A7,Dataset!$I$2:$I$201) -> 3211.82 | E7: =COUNTIF(Dataset!$A$2:$A$201,A7) -> 7 | F7: =RANK(C7,$C$4:$C$33,0) -> 10
A8: CUST005 | B8: =INDEX(Dataset!$B$2:$B$201,MATCH(A8,Dataset!$A$2:$A$201,0)) -> Robert Anderson | C8: =SUMIF(Dataset!$A$2:$A$201,A8,Dataset!$E$2:$E$201) -> 6666.13 | D8: =SUMIF(Dataset!$A$2:$A$201,A8,Dataset!$I$2:$I$201) -> 1982.39 | E8: =COUNTIF(Dataset!$A$2:$A$201,A8) -> 6 | F8: =RANK(C8,$C$4:$C$33,0) -> 14
A9: CUST006 | B9: =INDEX(Dataset!$B$2:$B$201,MATCH(A9,Dataset!$A$2:$A$201,0)) -> Mary Jackson | C9: =SUMIF(Dataset!$A$2:$A$201,A9,Dataset!$E$2:$E$201) -> 2699.75 | D9: =SUMIF(Dataset!$A$2:$A$201,A9,Dataset!$I$2:$I$201) -> 837.06 | E9: =COUNTIF(Dataset!$A$2:$A$201,A9) -> 2 | F9: =RANK(C9,$C$4:$C$33,0) -> 30
A10: CUST007 | B10: =INDEX(Dataset!$B$2:$B$201,MATCH(A10,Dataset!$A$2:$A$201,0)) -> Michael Anderson | C10: =SUMIF(Dataset!$A$2:$A$201,A10,Dataset!$E$2:$E$201) -> 9941.88 | D10: =SUMIF(Dataset!$A$2:$A$201,A10,Dataset!$I$2:$I$201) -> 3936.26 | E10: =COUNTIF(Dataset!$A$2:$A$201,A10) -> 10 | F10: =RANK(C10,$C$4:$C$33,0) -> 3
A11: CUST008 | B11: =INDEX(Dataset!$B$2:$B$201,MATCH(A11,Dataset!$A$2:$A$201,0)) -> Robert Anderson | C11: =SUMIF(Dataset!$A$2:$A$201,A11,Dataset!$E$2:$E$201) -> 9760.8 | D11: =SUMIF(Dataset!$A$2:$A$201,A11,Dataset!$I$2:$I$201) -> 3442.48 | E11: =COUNTIF(Dataset!$A$2:$A$201,A11) -> 10 | F11: =RANK(C11,$C$4:$C$33,0) -> 4
A12: CUST009 | B12: =INDEX(Dataset!$B$2:$B$201,MATCH(A12,Dataset!$A$2:$A$201,0)) -> Linda Jackson | C12: =SUMIF(Dataset!$A$2:$A$201,A12,Dataset!$E$2:$E$201) -> 6505.2 | D12: =SUMIF(Dataset!$A$2:$A$201,A12,Dataset!$I$2:$I$201) -> 2052.54 | E12: =COUNTIF(Dataset!$A$2:$A$201,A12) -> 7 | F12: =RANK(C12,$C$4:$C$33,0) -> 16
A13: CUST010 | B13: =INDEX(Dataset!$B$2:$B$201,MATCH(A13,Dataset!$A$2:$A$201,0)) -> David Thomas | C13: =SUMIF(Dataset!$A$2:$A$201,A13,Dataset!$E$2:$E$201) -> 4259.22 | D13: =SUMIF(Dataset!$A$2:$A$201,A13,Dataset!$I$2:$I$201) -> 1529.32 | E13: =COUNTIF(Dataset!$A$2:$A$201,A13) -> 5 | F13: =RANK(C13,$C$4:$C$33,0) -> 24
A14: CUST011 | B14: =INDEX(Dataset!$B$2:$B$201,MATCH(A14,Dataset!$A$2:$A$201,0)) -> Mary Davis | C14: =SUMIF(Dataset!$A$2:$A$201,A14,Dataset!$E$2:$E$201) -> 3762.29 | D14: =SUMIF(Dataset!$A$2:$A$201,A14,Dataset!$I$2:$I$201) -> 1545.04 | E14: =COUNTIF(Dataset!$A$2:$A$201,A14) -> 4 | F14: =RANK(C14,$C$4:$C$33,0) -> 27
A15: CUST012 | B15: =INDEX(Dataset!$B$2:$B$201,MATCH(A15,Dataset!$A$2:$A$201,0)) -> Robert Anderson | C15: =SUMIF(Dataset!$A$2:$A$201,A15,Dataset!$E$2:$E$201) -> 8339 | D15: =SUMIF(Dataset!$A$2:$A$201,A15,Dataset!$I$2:$I$201) -> 2988.71 | E15: =COUNTIF(Dataset!$A$2:$A$201,A15) -> 9 | F15: =RANK(C15,$C$4:$C$33,0) -> 8
... A33: CUST030 | B33: =INDEX(Dataset!$B$2:$B$201,MATCH(A33,Dataset!$A$2:$A$201,0)) -> James Wilson | C33: =SUMIF(Dataset!$A$2:$A$201,A33,Dataset!$E$2:$E$201) -> 7928.71 | D33: =SUMIF(Dataset!$A$2:$A$201,A33,Dataset!$I$2:$I$201) -> 2965.48 | E33: =COUNTIF(Dataset!$A$2:$A$201,A33) -> 9 | F33: =RANK(C33,$C$4:$C$33,0) -> 9

Sheet What-If Analysis
A1: WHAT IF Analysis - Discount vs Total Profit
A3: Discount Rate | B3: Projected Profit | C3: Change vs Current | D3: Profit Margin | E3: Comment | G3: Note
A4: 0 | B4: =SUMPRODUCT(Dataset!$E$2:$E$201*(1-A4)*0.4) -> 78087.104 | C4: =B4-$B$6 -> 7808.7104 | D4: =B4/SUM(Dataset!$E$2:$E$201) -> 0.4 | E4: Higher profit | G4: Dataset profit follows Sales × (1 − Discount) × 40%, so the WHAT IF table recalculates profit under alternative discounts.
A5: 0.05 | B5: =SUMPRODUCT(Dataset!$E$2:$E$201*(1-A5)*0.4) -> 74182.749 | C5: =B5-$B$6 -> 3904.3552 | D5: =B5/SUM(Dataset!$E$2:$E$201) -> 0.38 | E5: Higher profit
A6: Current 10% scenario | B6: =SUMPRODUCT(Dataset!$E$2:$E$201*(1-10%)*0.4) -> 70278.394 | C6: =B6-$B$6 -> 0 | D6: =B6/SUM(Dataset!$E$2:$E$201) -> 0.36 | E6: Baseline
A7: 0.15 | B7: =SUMPRODUCT(Dataset!$E$2:$E$201*(1-A7)*0.4) -> 66374.038 | C7: =B7-$B$6 -> -3904.3552 | D7: =B7/SUM(Dataset!$E$2:$E$201) -> 0.34 | E7: Lower profit
A8: 0.2 | B8: =SUMPRODUCT(Dataset!$E$2:$E$201*(1-A8)*0.4) -> 62469.683 | C8: =B8-$B$6 -> -7808.7104 | D8: =B8/SUM(Dataset!$E$2:$E$201) -> 0.32 | E8: Lower profit
A9: 0.25 | B9: =SUMPRODUCT(Dataset!$E$2:$E$201*(1-A9)*0.4) -> 58565.328 | C9: =B9-$B$6 -> -11713.066 | D9: =B9/SUM(Dataset!$E$2:$E$201) -> 0.3 | E9: Lower profit
A10: 0.3 | B10: =SUMPRODUCT(Dataset!$E$2:$E$201*(1-A10)*0.4) -> 54660.973 | C10: =B10-$B$6 -> -15617.421 | D10: =B10/SUM(Dataset!$E$2:$E$201) -> 0.28 | E10: Lower profit

Sheet Regression
A1: Linear Regression - Profit vs Sales
A3: Measure | B3: Value | D3: Regression Data | E3: Sales | F3: Profit
A4: Observations | B4: 200 | D4: Data | E4: 1036.09 | F4: 331.55
A5: Slope | B5: 0.35085599 | D5: Data | E5: 1101.28 | F5: 440.51
A6: Intercept | B6: -1.0315505 | D6: Data | E6: 713.34 | F6: 285.34
A7: R Square | B7: 0.5981523 | D7: Data | E7: 760.93 | F7: 161.7
A8: Correlation | B8: 10 | D8: Data | E8: 847 | F8: 271.04
A9: Standard Error (Y) | B9: 86.281231 | D9: Data | E9: 965.64 | F9: 304.18
A10: Standard Error (Slope) | B10: 0.020437189 | D10: Data | E10: 1317.53 | F10: 312.91
A11: t Statistic | B11: 10. Dashboard – KPI summary and visual insights. | D11: Data | E11: 1074.47 | F11: 300.85
D12: Data | E12: 501.54 | F12: 190.59
D13: Data | E13: 737.31 | F13: 350.22
A14: Interpretation | D14: Data | E14: 1572.82 | F14: 672.38
A15: R² = 0.598, meaning sales explain about 59.8% of the variation in profit in this dataset.
D17: Data | E17: 822.28 | F17: 273.41
D18: Data | E18: 521.67 | F18: 155.2
D19: Data | E19: 1502.93 | F19: 300.59
D20: Data | E20: 877.58 | F20: 298.38
D21: Data | E21: 636.7 | F21: 203.74
D22: Data | E22: 1506.14 | F22: 481.96
D23: Data | E23: 645.02 | F23: 161.26
D24: Data | E24: 953.3 | F24: 476.65
D25: Data | E25: 388.56 | F25: 82.57
D26: Data | E26: 743.17 | F26: 297.27
D27: Data | E27: 706.37 | F27: 176.59
D28: Data | E28: 925.31 | F28: 374.75
... D203: Data | E203: 928.32 | F203: 440.95

Sheet Descriptive Stats
A1: Descriptive Statistics
A3: Variable | B3: Count | C3: Mean | D3: Std Dev | E3: Min | F3: Max | G3: Median | H3: Range | I3: Total
A4: Sales | B4: 200 | C4: 976.0888 | D4: 299.27376 | E4: 258.51 | F4: 1923.66 | G4: 976.72 | H4: 1665.15 | I4: 195217.76
A5: Quantity | B5: 200 | C5: 9.995 | D5: 5.646627 | E5: 1 | F5: 19 | G5: 10 | H5: 18 | I5: 1999
A6: Discount | B6: 200 | C6: 0.09725 | D6: 0.072326295 | E6: 0 | F6: 0.2 | G6: 0.1 | H6: 0.2 | I6: 19.45
A7: Profit | B7: 200 | C7: 341.43505 | D7: 135.76619 | E7: 64.63 | F7: 769.46 | G7: 332.255 | H7: 704.83 | I7: 68287.01

Sheet Histogram
A1: Sales Histogram - Frequency Distribution
A3: Bin Start | B3: Bin End | C3: Frequency
A4: 258.51 | B4: 466.65375 | C4: 8
A5: 466.65375 | B5: 674.7975 | C5: 20
A6: 674.7975 | B6: 882.94125 | C6: 52
A7: 882.94125 | B7: 1091.085 | C7: 50
A8: 1091.085 | B8: 1299.2287 | C8: 42
A9: 1299.2287 | B9: 1507.3725 | C9: 21
A10: 1507.3725 | B10: 1715.5162 | C10: 6
A11: 1715.5162 | B11: 1923.66 | C11: 1

Sheet Monthly Growth
A1: Monthly Sales, Profit and Growth
A3: Month | B3: Sales | C3: Profit | D3: Quantity | E3: Growth | F3: Trend
A4: 2024-04 | B4: 19029.96 | C4: 6244.01 | D4: 176 | F4: —
A5: 2024-05 | B5: 18507.34 | C5: 6121.35 | D5: 227 | E5: =B5/B4-1 -> -0.027463011 | F5: =IF(E5>0,"↑",IF(E5<0,"↓","→")) -> ↓
A6: 2024-06 | B6: 20187.51 | C6: 6918 | D6: 198 | E6: =B6/B5-1 -> 0.090783981 | F6: =IF(E6>0,"↑",IF(E6<0,"↓","→")) -> ↑
A7: 2024-07 | B7: 11609.04 | C7: 3743.85 | D7: 120 | E7: =B7/B6-1 -> -0.42493948 | F7: =IF(E7>0,"↑",IF(E7<0,"↓","→")) -> ↓
A8: 2024-08 | B8: 10091.7 | C8: 3302.84 | D8: 98 | E8: =B8/B7-1 -> -0.13070331 | F8: =IF(E8>0,"↑",IF(E8<0,"↓","→")) -> ↓
A9: 2024-09 | B9: 20533.5 | C9: 7457.52 | D9: 200 | E9: =B9/B8-1 -> 1.0346919 | F9: =IF(E9>0,"↑",IF(E9<0,"↓","→")) -> ↑
A10: 2024-10 | B10: 14215.24 | C10: 4861.7 | D10: 146 | E10: =B10/B9-1 -> -0.30770497 | F10: =IF(E10>0,"↑",IF(E10<0,"↓","→")) -> ↓
A11: 2024-11 | B11: 20135.03 | C11: 6814.88 | D11: 167 | E11: =B11/B10-1 -> 0.41643968 | F11: =IF(E11>0,"↑",IF(E11<0,"↓","→")) -> ↑
A12: 2024-12 | B12: 11120.04 | C12: 3549.99 | D12: 134 | E12: =B12/B11-1 -> -0.44772667 | F12: =IF(E12>0,"↑",IF(E12<0,"↓","→")) -> ↓
A13: 2025-01 | B13: 14914.65 | C13: 5763.4 | D13: 162 | E13: =B13/B12-1 -> 0.34124068 | F13: =IF(E13>0,"↑",IF(E13<0,"↓","→")) -> ↑
A14: 2025-02 | B14: 14006.36 | C14: 5039.23 | D14: 132 | E14: =B14/B13-1 -> -0.060899183 | F14: =IF(E14>0,"↑",IF(E14<0,"↓","→")) -> ↓
A15: 2025-03 | B15: 17655.22 | C15: 7071.39 | D15: 209 | E15: =B15/B14-1 -> 0.26051451 | F15: =IF(E15>0,"↑",IF(E15<0,"↓","→")) -> ↑
A16: 2025-04 | B16: 3212.17 | C16: 1398.85 | D16: 30 | E16: =B16/B15-1 -> -0.81806117 | F16: =IF(E16>0,"↑",IF(E16<0,"↓","→")) -> ↓

Sheet High-Value Customers
A1: High-Value Customers - INDEX/MATCH + Filter
A3: Rank | B3: Customer_ID | C3: Customer_Name | D3: Total Purchase | E3: Total Profit | F3: Orders | G3: Status
A4: 1 | B4: CUST015 | C4: =INDEX(Dataset!$B$2:$B$201,MATCH(B4,Dataset!$A$2:$A$201,0)) -> Linda Taylor | D4: 11611.06 | E4: 4201.59 | F4: 11 | G4: High Value
A5: 2 | B5: CUST028 | C5: =INDEX(Dataset!$B$2:$B$201,MATCH(B5,Dataset!$A$2:$A$201,0)) -> Linda Taylor | D5: 10293.87 | E5: 3541.02 | F5: 12 | G5: High Value
A6: 3 | B6: CUST007 | C6: =INDEX(Dataset!$B$2:$B$201,MATCH(B6,Dataset!$A$2:$A$201,0)) -> Michael Anderson | D6: 9941.88 | E6: 3936.26 | F6: 10 | G6: High Value
A7: 4 | B7: CUST008 | C7: =INDEX(Dataset!$B$2:$B$201,MATCH(B7,Dataset!$A$2:$A$201,0)) -> Robert Anderson | D7: 9760.8 | E7: 3442.48 | F7: 10 | G7: High Value
A8: 5 | B8: CUST026 | C8: =INDEX(Dataset!$B$2:$B$201,MATCH(B8,Dataset!$A$2:$A$201,0)) -> Mary Davis | D8: 9371.81 | E8: 2922.02 | F8: 9 | G8: High Value
A9: 6 | B9: CUST021 | C9: =INDEX(Dataset!$B$2:$B$201,MATCH(B9,Dataset!$A$2:$A$201,0)) -> Sarah Anderson | D9: 8740.18 | E9: 2848.62 | F9: 8 | G9: High Value
A10: 7 | B10: CUST003 | C10: =INDEX(Dataset!$B$2:$B$201,MATCH(B10,Dataset!$A$2:$A$201,0)) -> Emma Davis | D10: 8490.18 | E10: 2652.75 | F10: 9 | G10: High Value
A11: 8 | B11: CUST012 | C11: =INDEX(Dataset!$B$2:$B$201,MATCH(B11,Dataset!$A$2:$A$201,0)) -> Robert Anderson | D11: 8339 | E11: 2988.71 | F11: 9 | G11: High Value
A12: 9 | B12: CUST030 | C12: =INDEX(Dataset!$B$2:$B$201,MATCH(B12,Dataset!$A$2:$A$201,0)) -> James Wilson | D12: 7928.71 | E12: 2965.48 | F12: 9 | G12: High Value
A13: 10 | B13: CUST004 | C13: =INDEX(Dataset!$B$2:$B$201,MATCH(B13,Dataset!$A$2:$A$201,0)) -> Lisa Thomas | D13: 7813.59 | E13: 3211.82 | F13: 7 | G13: High Value
A16: INDEX/MATCH Lookup
A17: Enter Customer ID | B17: CUST015
A18: Customer Name | B18: =INDEX(Dataset!$B$2:$B$201,MATCH(B17,Dataset!$A$2:$A$201,0)) -> Linda Taylor
A19: Total Purchase | B19: =SUMIF(Dataset!$A$2:$A$201,B17,Dataset!$E$2:$E$201) -> 11611.06
A20: Total Profit | B20: =SUMIF(Dataset!$A$2:$A$201,B17,Dataset!$I$2:$I$201) -> 4201.59

Sheet Pivot Analysis
A1: Pivot-Style Analysis - Total Sales by Region and Product
A3: Region | B3: Books | C3: Clothing | D3: Electronics | E3: Furniture | F3: Office Supplies | G3: Grand Total
A4: Central | B4: 11297.15 | C4: 12200.26 | D4: 6621.24 | E4: 4876.96 | F4: 8472.72 | G4: =SUM(B4:F4) -> 43468.33
A5: East | B5: 11389.09 | C5: 2401.45 | D5: 2869.54 | E5: 7592.34 | F5: 8189.22 | G5: =SUM(B5:F5) -> 32441.64
A6: North | B6: 8037.01 | C6: 8422.82 | D6: 8191.71 | E6: 6978.08 | F6: 3345.8 | G6: =SUM(B6:F6) -> 34975.42
A7: South | B7: 9588.04 | C7: 8393.63 | D7: 11989.07 | E7: 7982.73 | F7: 2295.32 | G7: =SUM(B7:F7) -> 40248.79
A8: West | B8: 6691.17 | C8: 10509.43 | D8: 11372.44 | E8: 9182.78 | F8: 6327.76 | G8: =SUM(B8:F8) -> 44083.58
A9: Grand Total | B9: =SUM(B4:B8) -> 47002.46 | C9: =SUM(C4:C8) -> 41927.59 | D9: =SUM(D4:D8) -> 41044 | E9: =SUM(E4:E8) -> 36612.89 | F9: =SUM(F4:F8) -> 28630.82 | G9: =SUM(G4:G8) -> 195217.76
A11: Product Category | B11: Total Sales | C11: Share of Sales
A12: Books | B12: 47002.46 | C12: =B12/$B$17 -> 0.24076938
A13: Clothing | B13: 41927.59 | C13: =B13/$B$17 -> 0.21477344
A14: Electronics | B14: 41044 | C14: =B14/$B$17 -> 0.21024726
A15: Furniture | B15: 36612.89 | C15: =B15/$B$17 -> 0.18754897
A16: Office Supplies | B16: 28630.82 | C16: =B16/$B$17 -> 0.14666094
A17: Total | B17: =SUM(B12:B16) -> 195217.76
